django_input_filter/__init__.py
django_input_filter/apps.py
django_input_filter/filters.py
django_input_filter/templates/django_input_filter/input_filter.html
django_input_filter-0.1.2.dist-info/METADATA
django_input_filter-0.1.2.dist-info/WHEEL
django_input_filter-0.1.2.dist-info/RECORD
