Metadata-Version: 2.1
Name: django-input-filter
Version: 0.1.2
Summary: A django library for input filters
Home-page: https://github.com/depis13/django-input-filter
License: MIT
Author: Denis Podshivalov
Author-email: denpodshivalov091@gmail.com
Requires-Python: >=3.6
Classifier: License :: OSI Approved :: MIT License
Classifier: Programming Language :: Python :: 3
Classifier: Programming Language :: Python :: 3.6
Classifier: Programming Language :: Python :: 3.7
Classifier: Programming Language :: Python :: 3.8
Classifier: Programming Language :: Python :: 3.9
Classifier: Programming Language :: Python :: 3.10
Classifier: Programming Language :: Python :: 3.11
Classifier: Programming Language :: Python :: 3.12
Requires-Dist: Django (>=3.2)
Project-URL: Repository, https://github.com/depis13/django-input-filter
